{
    "m_GameObject": {
        "m_FileID": 0,
        "m_PathID": 0
    },
    "m_Enabled": 1,
    "m_Script": {
        "m_FileID": 0,
        "m_PathID": 6943497729767635973
    },
    "m_Name": "skeleton_Data",
    "dataName": "1300900",
    "dragonBonesJSON": {
        "m_FileID": 0,
        "m_PathID": 5746052432979901669
    },
    "textureAtlas": [
        {
            "textureAtlasJSON": {
                "m_FileID": 0,
                "m_PathID": 5698804259764961691
            },
            "texture": {
                "m_FileID": 0,
                "m_PathID": -2765946757878734152
            },
            "material": {
                "m_FileID": 0,
                "m_PathID": 8825546768036652792
            },
            "uiMaterial": {
                "m_FileID": 0,
                "m_PathID": 7105052897559584145
            }
        }
    ]
}