{
    "m_GameObject": {
        "m_FileID": 0,
        "m_PathID": 0
    },
    "m_Enabled": 1,
    "m_Script": {
        "m_FileID": 0,
        "m_PathID": 6943497729767635973
    },
    "m_Name": "skeleton_Data",
    "dataName": "100359",
    "dragonBonesJSON": {
        "m_FileID": 0,
        "m_PathID": -1333596497962770691
    },
    "textureAtlas": [
        {
            "textureAtlasJSON": {
                "m_FileID": 0,
                "m_PathID": -3062577999280606689
            },
            "texture": {
                "m_FileID": 0,
                "m_PathID": -5162548524313377258
            },
            "material": {
                "m_FileID": 0,
                "m_PathID": -3534930718374594661
            },
            "uiMaterial": {
                "m_FileID": 0,
                "m_PathID": 3304221096211258917
            }
        }
    ]
}