{
    "m_GameObject": {
        "m_FileID": 0,
        "m_PathID": 0
    },
    "m_Enabled": 1,
    "m_Script": {
        "m_FileID": 0,
        "m_PathID": 6943497729767635973
    },
    "m_Name": "skeleton_Data",
    "dataName": "1713070",
    "dragonBonesJSON": {
        "m_FileID": 0,
        "m_PathID": -166731698780016502
    },
    "textureAtlas": [
        {
            "textureAtlasJSON": {
                "m_FileID": 0,
                "m_PathID": 7681581787009615558
            },
            "texture": {
                "m_FileID": 0,
                "m_PathID": -4911533830356909227
            },
            "material": {
                "m_FileID": 0,
                "m_PathID": 3700892991068221561
            },
            "uiMaterial": {
                "m_FileID": 0,
                "m_PathID": -1697546469959608701
            }
        }
    ]
}