{
    "m_GameObject": {
        "m_FileID": 0,
        "m_PathID": 0
    },
    "m_Enabled": 1,
    "m_Script": {
        "m_FileID": 0,
        "m_PathID": 6943497729767635973
    },
    "m_Name": "skeleton_Data",
    "dataName": "1300616",
    "dragonBonesJSON": {
        "m_FileID": 0,
        "m_PathID": 869802629564971316
    },
    "textureAtlas": [
        {
            "textureAtlasJSON": {
                "m_FileID": 0,
                "m_PathID": 3178532770142799605
            },
            "texture": {
                "m_FileID": 0,
                "m_PathID": -6734538393750422604
            },
            "material": {
                "m_FileID": 0,
                "m_PathID": 2577981212649182223
            },
            "uiMaterial": {
                "m_FileID": 0,
                "m_PathID": 708869957744625855
            }
        }
    ]
}