{
    "m_GameObject": {
        "m_FileID": 0,
        "m_PathID": 0
    },
    "m_Enabled": 1,
    "m_Script": {
        "m_FileID": 0,
        "m_PathID": 6943497729767635973
    },
    "m_Name": "skeleton_Data",
    "dataName": "100155",
    "dragonBonesJSON": {
        "m_FileID": 0,
        "m_PathID": 1936123003143834796
    },
    "textureAtlas": [
        {
            "textureAtlasJSON": {
                "m_FileID": 0,
                "m_PathID": 4179059553234946208
            },
            "texture": {
                "m_FileID": 0,
                "m_PathID": 6387165584661882466
            },
            "material": {
                "m_FileID": 0,
                "m_PathID": -6588430687260407206
            },
            "uiMaterial": {
                "m_FileID": 0,
                "m_PathID": 4724133733514189044
            }
        }
    ]
}