{
    "m_GameObject": {
        "m_FileID": 0,
        "m_PathID": 0
    },
    "m_Enabled": 1,
    "m_Script": {
        "m_FileID": 0,
        "m_PathID": 6943497729767635973
    },
    "m_Name": "skeleton_Data",
    "dataName": "1300501",
    "dragonBonesJSON": {
        "m_FileID": 0,
        "m_PathID": 7788207765006745093
    },
    "textureAtlas": [
        {
            "textureAtlasJSON": {
                "m_FileID": 0,
                "m_PathID": 3621777016800178823
            },
            "texture": {
                "m_FileID": 0,
                "m_PathID": -6731130840355138480
            },
            "material": {
                "m_FileID": 0,
                "m_PathID": 5428435351639008457
            },
            "uiMaterial": {
                "m_FileID": 0,
                "m_PathID": 8753727122320875633
            }
        }
    ]
}