{
    "m_GameObject": {
        "m_FileID": 0,
        "m_PathID": 0
    },
    "m_Enabled": 1,
    "m_Script": {
        "m_FileID": 0,
        "m_PathID": 6943497729767635973
    },
    "m_Name": "skeleton_Data",
    "dataName": "1300848_2",
    "dragonBonesJSON": {
        "m_FileID": 0,
        "m_PathID": -5307641591556601676
    },
    "textureAtlas": [
        {
            "textureAtlasJSON": {
                "m_FileID": 0,
                "m_PathID": 1445562214116678955
            },
            "texture": {
                "m_FileID": 0,
                "m_PathID": 3768588601284833702
            },
            "material": {
                "m_FileID": 0,
                "m_PathID": -6078952474611146191
            },
            "uiMaterial": {
                "m_FileID": 0,
                "m_PathID": 2842481819402218740
            }
        }
    ]
}