{
    "m_GameObject": {
        "m_FileID": 0,
        "m_PathID": 0
    },
    "m_Enabled": 1,
    "m_Script": {
        "m_FileID": 0,
        "m_PathID": 6943497729767635973
    },
    "m_Name": "skeleton_Data",
    "dataName": "1301060_1",
    "dragonBonesJSON": {
        "m_FileID": 0,
        "m_PathID": -8401380171247681698
    },
    "textureAtlas": [
        {
            "textureAtlasJSON": {
                "m_FileID": 0,
                "m_PathID": 3695479035288315773
            },
            "texture": {
                "m_FileID": 0,
                "m_PathID": -5923340691405173525
            },
            "material": {
                "m_FileID": 0,
                "m_PathID": -6963285572449943009
            },
            "uiMaterial": {
                "m_FileID": 0,
                "m_PathID": -1126793855594301951
            }
        }
    ]
}