{
    "m_GameObject": {
        "m_FileID": 0,
        "m_PathID": 0
    },
    "m_Enabled": 1,
    "m_Script": {
        "m_FileID": 0,
        "m_PathID": 6943497729767635973
    },
    "m_Name": "skeleton_Data",
    "dataName": "1300596_2",
    "dragonBonesJSON": {
        "m_FileID": 0,
        "m_PathID": 3554702158925126407
    },
    "textureAtlas": [
        {
            "textureAtlasJSON": {
                "m_FileID": 0,
                "m_PathID": 7678665187750589913
            },
            "texture": {
                "m_FileID": 0,
                "m_PathID": -1130398026047210880
            },
            "material": {
                "m_FileID": 0,
                "m_PathID": -3978717254839581394
            },
            "uiMaterial": {
                "m_FileID": 0,
                "m_PathID": 4405240259268711328
            }
        }
    ]
}