{
    "m_GameObject": {
        "m_FileID": 0,
        "m_PathID": 0
    },
    "m_Enabled": 1,
    "m_Script": {
        "m_FileID": 0,
        "m_PathID": 6943497729767635973
    },
    "m_Name": "skeleton_Data",
    "dataName": "1300536",
    "dragonBonesJSON": {
        "m_FileID": 0,
        "m_PathID": -6799107754573839505
    },
    "textureAtlas": [
        {
            "textureAtlasJSON": {
                "m_FileID": 0,
                "m_PathID": 4870261029483491911
            },
            "texture": {
                "m_FileID": 0,
                "m_PathID": 2265637293361376588
            },
            "material": {
                "m_FileID": 0,
                "m_PathID": -7531034394859395338
            },
            "uiMaterial": {
                "m_FileID": 0,
                "m_PathID": -4616177974727024356
            }
        }
    ]
}