{
    "m_GameObject": {
        "m_FileID": 0,
        "m_PathID": 0
    },
    "m_Enabled": 1,
    "m_Script": {
        "m_FileID": 0,
        "m_PathID": 6943497729767635973
    },
    "m_Name": "skeleton_Data",
    "dataName": "1300545",
    "dragonBonesJSON": {
        "m_FileID": 0,
        "m_PathID": 7065916371527002635
    },
    "textureAtlas": [
        {
            "textureAtlasJSON": {
                "m_FileID": 0,
                "m_PathID": -660695498685978580
            },
            "texture": {
                "m_FileID": 0,
                "m_PathID": -5171227865102170160
            },
            "material": {
                "m_FileID": 0,
                "m_PathID": 4864871144996826708
            },
            "uiMaterial": {
                "m_FileID": 0,
                "m_PathID": -8310078519798866835
            }
        }
    ]
}