{
    "m_GameObject": {
        "m_FileID": 0,
        "m_PathID": 0
    },
    "m_Enabled": 1,
    "m_Script": {
        "m_FileID": 0,
        "m_PathID": 6943497729767635973
    },
    "m_Name": "skeleton_Data",
    "dataName": "1300267",
    "dragonBonesJSON": {
        "m_FileID": 0,
        "m_PathID": 5956898123102922216
    },
    "textureAtlas": [
        {
            "textureAtlasJSON": {
                "m_FileID": 0,
                "m_PathID": -4784788042489172359
            },
            "texture": {
                "m_FileID": 0,
                "m_PathID": -7836363973484584461
            },
            "material": {
                "m_FileID": 0,
                "m_PathID": -3866780249497100931
            },
            "uiMaterial": {
                "m_FileID": 0,
                "m_PathID": -2338062054046184976
            }
        }
    ]
}