{
    "m_GameObject": {
        "m_FileID": 0,
        "m_PathID": 0
    },
    "m_Enabled": 1,
    "m_Script": {
        "m_FileID": 0,
        "m_PathID": 6943497729767635973
    },
    "m_Name": "skeleton_Data",
    "dataName": "1300996_1",
    "dragonBonesJSON": {
        "m_FileID": 0,
        "m_PathID": 7678103887441915033
    },
    "textureAtlas": [
        {
            "textureAtlasJSON": {
                "m_FileID": 0,
                "m_PathID": 9042003682732775152
            },
            "texture": {
                "m_FileID": 0,
                "m_PathID": -4506984792271865140
            },
            "material": {
                "m_FileID": 0,
                "m_PathID": 5220215381449606327
            },
            "uiMaterial": {
                "m_FileID": 0,
                "m_PathID": 3712238753104419628
            }
        }
    ]
}