{
    "m_GameObject": {
        "m_FileID": 0,
        "m_PathID": 0
    },
    "m_Enabled": 1,
    "m_Script": {
        "m_FileID": 0,
        "m_PathID": 6943497729767635973
    },
    "m_Name": "skeleton_Data",
    "dataName": "100431",
    "dragonBonesJSON": {
        "m_FileID": 0,
        "m_PathID": -4718181188153825170
    },
    "textureAtlas": [
        {
            "textureAtlasJSON": {
                "m_FileID": 0,
                "m_PathID": 3226717752049957728
            },
            "texture": {
                "m_FileID": 0,
                "m_PathID": 7193372307336905373
            },
            "material": {
                "m_FileID": 0,
                "m_PathID": -5501031263439813320
            },
            "uiMaterial": {
                "m_FileID": 0,
                "m_PathID": -7690295507842124493
            }
        }
    ]
}